LICENSE
MANIFEST.in
README.md
package.json
setup.py
dash_monaco_editor/DashMonacoEditor.py
dash_monaco_editor/__init__.py
dash_monaco_editor/_imports_.py
dash_monaco_editor/dash_monaco_editor.min.js
dash_monaco_editor/dash_monaco_editor.min.js.map
dash_monaco_editor/metadata.json
dash_monaco_editor/package-info.json
dash_monaco_editor.egg-info/PKG-INFO
dash_monaco_editor.egg-info/SOURCES.txt
dash_monaco_editor.egg-info/dependency_links.txt
dash_monaco_editor.egg-info/top_level.txt