Metadata-Version: 2.1
Name: dash-monaco-editor
Version: 0.0.1
Summary: Plotly dash Monaco Editor Component
Author: Siddhartha Chakraborty <techiesid1985@gmail.com>
License: MIT
Classifier: Framework :: Dash
License-File: LICENSE
